translatekit/__init__.py
translatekit/baidu.py
translatekit/base.py
translatekit/deepl.py
translatekit/google.py
translatekit/kit.py
translatekit/libre.py
translatekit/linguee.py
translatekit/llm_general.py
translatekit/microsoft.py
translatekit/mymemory.py
translatekit/null_translator.py
translatekit/papago.py
translatekit/pons.py
translatekit/qcri.py
translatekit/sizhi.py
translatekit/tencent-hunyuan.py
translatekit/tencent.py
translatekit/test2.py
translatekit/test_ai.py
translatekit/test_ai_pro.py
translatekit/test_format.py
translatekit/test_re.py
translatekit/test_self.py
translatekit/yandex.py
translatekit/youdao.py
translatekit-0.2.7.dist-info/LICENSE
translatekit-0.2.7.dist-info/METADATA
translatekit-0.2.7.dist-info/WHEEL
translatekit-0.2.7.dist-info/top_level.txt
translatekit-0.2.7.dist-info/RECORD
