Metadata-Version: 2.1
Name: translatekit
Version: 0.2.7
Summary: 一个简单快捷的翻译服务工具包，支持自定义脚本扩展
Home-page: https://github.com/HZBHZB1234/Py-Translate-Kit
Author: HZBHZB1234
Author-email: HZBHZB1234 <HZBHZB1234@outlook.com>
License: MIT License
Project-URL: Homepage, https://github.com/HZBHZB1234/Py-Translate-Kit
Classifier: Development Status :: 3 - Alpha
Classifier: Intended Audience :: Developers
Classifier: License :: OSI Approved :: MIT License
Classifier: Operating System :: OS Independent
Classifier: Programming Language :: Python :: 3
Classifier: Programming Language :: Python :: 3.7
Classifier: Programming Language :: Python :: 3.8
Classifier: Programming Language :: Python :: 3.9
Classifier: Programming Language :: Python :: 3.10
Requires-Python: >=3.6.0
License-File: LICENSE
Requires-Dist: requests>=2.25.1
Requires-Dist: beautifulsoup4>=4.9.3
Requires-Dist: jsonpatch>=1.26
Provides-Extra: extras
